erdesktop/__init__.py
erdesktop/app_main.py
erdesktop/main_window.py
erdesktop/cloud/__init__.py
erdesktop/cloud/cloud.py
erdesktop/cloud/routes.py
erdesktop/cloud/status.py
erdesktop/dialogs/__init__.py
erdesktop/dialogs/about_dialog.py
erdesktop/dialogs/account_dialog.py
erdesktop/dialogs/backup_dialog.py
erdesktop/dialogs/event_details_dialog.py
erdesktop/dialogs/settings_dialog.py
erdesktop/resources/__init__.py
erdesktop/resources/languages.py
erdesktop/resources/images/ico/app-icon-default.ico
erdesktop/resources/images/ico/app-icon-small.ico
erdesktop/resources/images/png/app-icon-default.png
erdesktop/resources/images/png/app-icon-small.png
erdesktop/settings/__init__.py
erdesktop/settings/default.py
erdesktop/settings/settings.py
erdesktop/settings/theme.py
erdesktop/settings/type_conv.py
erdesktop/storage/__init__.py
erdesktop/storage/models.py
erdesktop/storage/sql.py
erdesktop/storage/storage.py
erdesktop/system/__init__.py
erdesktop/system/autostart.py
erdesktop/system/linux.py
erdesktop/system/shortcut_icon.py
erdesktop/system/system.py
erdesktop/system/windows.py
erdesktop/util/__init__.py
erdesktop/util/decorators.py
erdesktop/util/exceptions.py
erdesktop/util/logger.py
erdesktop/util/notification.py
erdesktop/util/service.py
erdesktop/util/worker.py
erdesktop/widgets/__init__.py
erdesktop/widgets/backup_widget.py
erdesktop/widgets/calendar_widget.py
erdesktop/widgets/event_list_widget.py
erdesktop/widgets/event_widget.py
erdesktop/widgets/waiting_spinner.py
erdesktop/widgets/util/__init__.py
erdesktop/widgets/util/buttons.py
erdesktop/widgets/util/popup.py
tests/unittests/__init__.py
tests/unittests/storage/__init__.py
tests/unittests/storage/test_models.py
tests/unittests/storage/test_storage.py
erdesktop-2019.1.0b0.dist-info/LICENSE
erdesktop-2019.1.0b0.dist-info/METADATA
erdesktop-2019.1.0b0.dist-info/WHEEL
erdesktop-2019.1.0b0.dist-info/entry_points.txt
erdesktop-2019.1.0b0.dist-info/top_level.txt
erdesktop-2019.1.0b0.dist-info/RECORD
