Metadata-Version: 2.1
Name: erdesktop
Version: 2019.1.0b0
Summary: Desktop application which helps to finish all tasks in time
Home-page: https://github.com/YuriyLisovskiy/EventReminder
Author: Yuriy Lisovskiy
Author-email: yuralisovskiy98@gmail.com
License: GPLv3
Platform: UNKNOWN
Classifier: License :: OSI Approved :: GNU General Public License v3 (GPLv3)
Classifier: Programming Language :: Python :: 3.6
Classifier: Operating System :: POSIX :: Linux
Classifier: Operating System :: Microsoft :: Windows
Requires-Python: >=3.6.0
Requires-Dist: PyQt5 (==5.11.3)
Requires-Dist: requests (==2.21.0)
Requires-Dist: QtAwesome (==0.5.7)
